{
  "projects": [
    {
      "name": "manutenção",
      "budget": "2344",
      "category": {
        "id": "2",
        "name": "Desenvolvimento"
      },
      "cost": 0,
      "services": [],
      "id": 1
    },
    {
      "name": "testes",
      "budget": "9855",
      "cost": 0,
      "services": [],
      "id": 2
    },
    {
      "name": "services",
      "budget": "18500",
      "cost": 0,
      "services": [],
      "id": 3
    }
  ],
  "categories": [
    {
      "id": 1,
      "name": "Infra"
    },
    {
      "id": 2,
      "name": "Desenvolvimento"
    },
    {
      "id": 3,
      "name": "Desing"
    },
    {
      "id": 4,
      "name": "Planejamento"
    }
  ]
}